{
  "two_leg": [
    {
      "legs": [
        {
          "id": 1630558,
          "name": "Davion Mitchell",
          "team": "MIA",
          "position": "G",
          "stat": "pr",
          "label": "Pts+Rebs",
          "odds_type": "standard",
          "line": 9.5,
          "hit_rate": 0.8,
          "hit_rate_l5": 1.0,
          "hit_rate_season": 0.702,
          "avg_l5": 17.0,
          "avg_l10": 12.5,
          "avg_season": 11.7,
          "edge": 7.5,
          "hits": 8,
          "sample": 10,
          "matchup_mult": 0.974,
          "opponent": "CHA",
          "location": "Road",
          "streak": {
            "count": 5,
            "type": "hit"
          },
          "confidence": 84.9
        },
        {
          "id": 1630224,
          "name": "Jalen Green",
          "team": "PHX",
          "position": "G",
          "stat": "pr",
          "label": "Pts+Rebs",
          "odds_type": "standard",
          "line": 27.5,
          "hit_rate": 0.6,
          "hit_rate_l5": 1.0,
          "hit_rate_season": 0.4,
          "avg_l5": 32.6,
          "avg_l10": 26.1,
          "avg_season": 21.1,
          "edge": 5.1,
          "hits": 6,
          "sample": 10,
          "matchup_mult": 0.999,
          "opponent": "MIN",
          "location": "Road",
          "streak": {
            "count": 6,
            "type": "hit"
          },
          "confidence": 81.0
        }
      ],
      "score": 83.0,
      "correlated": false
    },
    {
      "legs": [
        {
          "id": 1630558,
          "name": "Davion Mitchell",
          "team": "MIA",
          "position": "G",
          "stat": "pts",
          "label": "Points",
          "odds_type": "standard",
          "line": 7.5,
          "hit_rate": 0.8,
          "hit_rate_l5": 1.0,
          "hit_rate_season": 0.702,
          "avg_l5": 13.0,
          "avg_l10": 9.1,
          "avg_season": 9.0,
          "edge": 5.5,
          "hits": 8,
          "sample": 10,
          "matchup_mult": 0.974,
          "opponent": "CHA",
          "location": "Road",
          "streak": {
            "count": 5,
            "type": "hit"
          },
          "confidence": 84.9
        },
        {
          "id": 1630224,
          "name": "Jalen Green",
          "team": "PHX",
          "position": "G",
          "stat": "pr",
          "label": "Pts+Rebs",
          "odds_type": "standard",
          "line": 27.5,
          "hit_rate": 0.6,
          "hit_rate_l5": 1.0,
          "hit_rate_season": 0.4,
          "avg_l5": 32.6,
          "avg_l10": 26.1,
          "avg_season": 21.1,
          "edge": 5.1,
          "hits": 6,
          "sample": 10,
          "matchup_mult": 0.999,
          "opponent": "MIN",
          "location": "Road",
          "streak": {
            "count": 6,
            "type": "hit"
          },
          "confidence": 81.0
        }
      ],
      "score": 83.0,
      "correlated": false
    },
    {
      "legs": [
        {
          "id": 1630558,
          "name": "Davion Mitchell",
          "team": "MIA",
          "position": "G",
          "stat": "pr",
          "label": "Pts+Rebs",
          "odds_type": "standard",
          "line": 9.5,
          "hit_rate": 0.8,
          "hit_rate_l5": 1.0,
          "hit_rate_season": 0.702,
          "avg_l5": 17.0,
          "avg_l10": 12.5,
          "avg_season": 11.7,
          "edge": 7.5,
          "hits": 8,
          "sample": 10,
          "matchup_mult": 0.974,
          "opponent": "CHA",
          "location": "Road",
          "streak": {
            "count": 5,
            "type": "hit"
          },
          "confidence": 84.9
        },
        {
          "id": 201566,
          "name": "Russell Westbrook",
          "team": "SAC",
          "position": "G",
          "stat": "ast",
          "label": "Assists",
          "odds_type": "standard",
          "line": 6.5,
          "hit_rate": 0.6,
          "hit_rate_l5": 1.0,
          "hit_rate_season": 0.484,
          "avg_l5": 9.7,
          "avg_l10": 6.6,
          "avg_season": 6.6,
          "edge": 3.2,
          "hits": 6,
          "sample": 10,
          "matchup_mult": 0.979,
          "opponent": "SAS",
          "location": "Home",
          "streak": {
            "count": 5,
            "type": "hit"
          },
          "confidence": 79.9
        }
      ],
      "score": 82.4,
      "correlated": false
    },
    {
      "legs": [
        {
          "id": 1630558,
          "name": "Davion Mitchell",
          "team": "MIA",
          "position": "G",
          "stat": "pts",
          "label": "Points",
          "odds_type": "standard",
          "line": 7.5,
          "hit_rate": 0.8,
          "hit_rate_l5": 1.0,
          "hit_rate_season": 0.702,
          "avg_l5": 13.0,
          "avg_l10": 9.1,
          "avg_season": 9.0,
          "edge": 5.5,
          "hits": 8,
          "sample": 10,
          "matchup_mult": 0.974,
          "opponent": "CHA",
          "location": "Road",
          "streak": {
            "count": 5,
            "type": "hit"
          },
          "confidence": 84.9
        },
        {
          "id": 201566,
          "name": "Russell Westbrook",
          "team": "SAC",
          "position": "G",
          "stat": "ast",
          "label": "Assists",
          "odds_type": "standard",
          "line": 6.5,
          "hit_rate": 0.6,
          "hit_rate_l5": 1.0,
          "hit_rate_season": 0.484,
          "avg_l5": 9.7,
          "avg_l10": 6.6,
          "avg_season": 6.6,
          "edge": 3.2,
          "hits": 6,
          "sample": 10,
          "matchup_mult": 0.979,
          "opponent": "SAS",
          "location": "Home",
          "streak": {
            "count": 5,
            "type": "hit"
          },
          "confidence": 79.9
        }
      ],
      "score": 82.4,
      "correlated": false
    },
    {
      "legs": [
        {
          "id": 1630558,
          "name": "Davion Mitchell",
          "team": "MIA",
          "position": "G",
          "stat": "pr",
          "label": "Pts+Rebs",
          "odds_type": "standard",
          "line": 9.5,
          "hit_rate": 0.8,
          "hit_rate_l5": 1.0,
          "hit_rate_season": 0.702,
          "avg_l5": 17.0,
          "avg_l10": 12.5,
          "avg_season": 11.7,
          "edge": 7.5,
          "hits": 8,
          "sample": 10,
          "matchup_mult": 0.974,
          "opponent": "CHA",
          "location": "Road",
          "streak": {
            "count": 5,
            "type": "hit"
          },
          "confidence": 84.9
        },
        {
          "id": 1626164,
          "name": "Devin Booker",
          "team": "PHX",
          "position": "G",
          "stat": "pr",
          "label": "Pts+Rebs",
          "odds_type": "standard",
          "line": 31.5,
          "hit_rate": 0.7,
          "hit_rate_l5": 1.0,
          "hit_rate_season": 0.423,
          "avg_l5": 38.4,
          "avg_l10": 33.9,
          "avg_season": 29.7,
          "edge": 6.9,
          "hits": 7,
          "sample": 10,
          "matchup_mult": 0.999,
          "opponent": "MIN",
          "location": "Road",
          "streak": {
            "count": 7,
            "type": "hit"
          },
          "confidence": 78.8
        }
      ],
      "score": 81.8,
      "correlated": false
    },
    {
      "legs": [
        {
          "id": 1630558,
          "name": "Davion Mitchell",
          "team": "MIA",
          "position": "G",
          "stat": "pts",
          "label": "Points",
          "odds_type": "standard",
          "line": 7.5,
          "hit_rate": 0.8,
          "hit_rate_l5": 1.0,
          "hit_rate_season": 0.702,
          "avg_l5": 13.0,
          "avg_l10": 9.1,
          "avg_season": 9.0,
          "edge": 5.5,
          "hits": 8,
          "sample": 10,
          "matchup_mult": 0.974,
          "opponent": "CHA",
          "location": "Road",
          "streak": {
            "count": 5,
            "type": "hit"
          },
          "confidence": 84.9
        },
        {
          "id": 1626164,
          "name": "Devin Booker",
          "team": "PHX",
          "position": "G",
          "stat": "pr",
          "label": "Pts+Rebs",
          "odds_type": "standard",
          "line": 31.5,
          "hit_rate": 0.7,
          "hit_rate_l5": 1.0,
          "hit_rate_season": 0.423,
          "avg_l5": 38.4,
          "avg_l10": 33.9,
          "avg_season": 29.7,
          "edge": 6.9,
          "hits": 7,
          "sample": 10,
          "matchup_mult": 0.999,
          "opponent": "MIN",
          "location": "Road",
          "streak": {
            "count": 7,
            "type": "hit"
          },
          "confidence": 78.8
        }
      ],
      "score": 81.8,
      "correlated": false
    },
    {
      "legs": [
        {
          "id": 1630558,
          "name": "Davion Mitchell",
          "team": "MIA",
          "position": "G",
          "stat": "pr",
          "label": "Pts+Rebs",
          "odds_type": "standard",
          "line": 9.5,
          "hit_rate": 0.8,
          "hit_rate_l5": 1.0,
          "hit_rate_season": 0.702,
          "avg_l5": 17.0,
          "avg_l10": 12.5,
          "avg_season": 11.7,
          "edge": 7.5,
          "hits": 8,
          "sample": 10,
          "matchup_mult": 0.974,
          "opponent": "CHA",
          "location": "Road",
          "streak": {
            "count": 5,
            "type": "hit"
          },
          "confidence": 84.9
        },
        {
          "id": 1641724,
          "name": "Jett Howard",
          "team": "ORL",
          "position": "G",
          "stat": "pr",
          "label": "Pts+Rebs",
          "odds_type": "standard",
          "line": 8.5,
          "hit_rate": 0.7,
          "hit_rate_l5": 1.0,
          "hit_rate_season": 0.356,
          "avg_l5": 13.4,
          "avg_l10": 11.6,
          "avg_season": 6.4,
          "edge": 4.9,
          "hits": 7,
          "sample": 10,
          "matchup_mult": 0.934,
          "opponent": "OKC",
          "location": "Home",
          "streak": {
            "count": 6,
            "type": "hit"
          },
          "confidence": 76.1
        }
      ],
      "score": 80.5,
      "correlated": false
    },
    {
      "legs": [
        {
          "id": 1630558,
          "name": "Davion Mitchell",
          "team": "MIA",
          "position": "G",
          "stat": "pts",
          "label": "Points",
          "odds_type": "standard",
          "line": 7.5,
          "hit_rate": 0.8,
          "hit_rate_l5": 1.0,
          "hit_rate_season": 0.702,
          "avg_l5": 13.0,
          "avg_l10": 9.1,
          "avg_season": 9.0,
          "edge": 5.5,
          "hits": 8,
          "sample": 10,
          "matchup_mult": 0.974,
          "opponent": "CHA",
          "location": "Road",
          "streak": {
            "count": 5,
            "type": "hit"
          },
          "confidence": 84.9
        },
        {
          "id": 1641724,
          "name": "Jett Howard",
          "team": "ORL",
          "position": "G",
          "stat": "pr",
          "label": "Pts+Rebs",
          "odds_type": "standard",
          "line": 8.5,
          "hit_rate": 0.7,
          "hit_rate_l5": 1.0,
          "hit_rate_season": 0.356,
          "avg_l5": 13.4,
          "avg_l10": 11.6,
          "avg_season": 6.4,
          "edge": 4.9,
          "hits": 7,
          "sample": 10,
          "matchup_mult": 0.934,
          "opponent": "OKC",
          "location": "Home",
          "streak": {
            "count": 6,
            "type": "hit"
          },
          "confidence": 76.1
        }
      ],
      "score": 80.5,
      "correlated": false
    },
    {
      "legs": [
        {
          "id": 1630224,
          "name": "Jalen Green",
          "team": "PHX",
          "position": "G",
          "stat": "pr",
          "label": "Pts+Rebs",
          "odds_type": "standard",
          "line": 27.5,
          "hit_rate": 0.6,
          "hit_rate_l5": 1.0,
          "hit_rate_season": 0.4,
          "avg_l5": 32.6,
          "avg_l10": 26.1,
          "avg_season": 21.1,
          "edge": 5.1,
          "hits": 6,
          "sample": 10,
          "matchup_mult": 0.999,
          "opponent": "MIN",
          "location": "Road",
          "streak": {
            "count": 6,
            "type": "hit"
          },
          "confidence": 81.0
        },
        {
          "id": 201566,
          "name": "Russell Westbrook",
          "team": "SAC",
          "position": "G",
          "stat": "ast",
          "label": "Assists",
          "odds_type": "standard",
          "line": 6.5,
          "hit_rate": 0.6,
          "hit_rate_l5": 1.0,
          "hit_rate_season": 0.484,
          "avg_l5": 9.7,
          "avg_l10": 6.6,
          "avg_season": 6.6,
          "edge": 3.2,
          "hits": 6,
          "sample": 10,
          "matchup_mult": 0.979,
          "opponent": "SAS",
          "location": "Home",
          "streak": {
            "count": 5,
            "type": "hit"
          },
          "confidence": 79.9
        }
      ],
      "score": 80.4,
      "correlated": false
    },
    {
      "legs": [
        {
          "id": 1630558,
          "name": "Davion Mitchell",
          "team": "MIA",
          "position": "G",
          "stat": "pr",
          "label": "Pts+Rebs",
          "odds_type": "standard",
          "line": 9.5,
          "hit_rate": 0.8,
          "hit_rate_l5": 1.0,
          "hit_rate_season": 0.702,
          "avg_l5": 17.0,
          "avg_l10": 12.5,
          "avg_season": 11.7,
          "edge": 7.5,
          "hits": 8,
          "sample": 10,
          "matchup_mult": 0.974,
          "opponent": "CHA",
          "location": "Road",
          "streak": {
            "count": 5,
            "type": "hit"
          },
          "confidence": 84.9
        },
        {
          "id": 1641724,
          "name": "Jett Howard",
          "team": "ORL",
          "position": "G",
          "stat": "pra",
          "label": "Pts+Rebs+Asts",
          "odds_type": "standard",
          "line": 9.0,
          "hit_rate": 0.7,
          "hit_rate_l5": 1.0,
          "hit_rate_season": 0.311,
          "avg_l5": 14.4,
          "avg_l10": 12.8,
          "avg_season": 7.2,
          "edge": 5.4,
          "hits": 7,
          "sample": 10,
          "matchup_mult": 0.934,
          "opponent": "OKC",
          "location": "Home",
          "streak": {
            "count": 6,
            "type": "hit"
          },
          "confidence": 75.5
        }
      ],
      "score": 80.2,
      "correlated": false
    }
  ],
  "three_leg": [
    {
      "legs": [
        {
          "id": 1630558,
          "name": "Davion Mitchell",
          "team": "MIA",
          "position": "G",
          "stat": "pr",
          "label": "Pts+Rebs",
          "odds_type": "standard",
          "line": 9.5,
          "hit_rate": 0.8,
          "hit_rate_l5": 1.0,
          "hit_rate_season": 0.702,
          "avg_l5": 17.0,
          "avg_l10": 12.5,
          "avg_season": 11.7,
          "edge": 7.5,
          "hits": 8,
          "sample": 10,
          "matchup_mult": 0.974,
          "opponent": "CHA",
          "location": "Road",
          "streak": {
            "count": 5,
            "type": "hit"
          },
          "confidence": 84.9
        },
        {
          "id": 1630224,
          "name": "Jalen Green",
          "team": "PHX",
          "position": "G",
          "stat": "pr",
          "label": "Pts+Rebs",
          "odds_type": "standard",
          "line": 27.5,
          "hit_rate": 0.6,
          "hit_rate_l5": 1.0,
          "hit_rate_season": 0.4,
          "avg_l5": 32.6,
          "avg_l10": 26.1,
          "avg_season": 21.1,
          "edge": 5.1,
          "hits": 6,
          "sample": 10,
          "matchup_mult": 0.999,
          "opponent": "MIN",
          "location": "Road",
          "streak": {
            "count": 6,
            "type": "hit"
          },
          "confidence": 81.0
        },
        {
          "id": 201566,
          "name": "Russell Westbrook",
          "team": "SAC",
          "position": "G",
          "stat": "ast",
          "label": "Assists",
          "odds_type": "standard",
          "line": 6.5,
          "hit_rate": 0.6,
          "hit_rate_l5": 1.0,
          "hit_rate_season": 0.484,
          "avg_l5": 9.7,
          "avg_l10": 6.6,
          "avg_season": 6.6,
          "edge": 3.2,
          "hits": 6,
          "sample": 10,
          "matchup_mult": 0.979,
          "opponent": "SAS",
          "location": "Home",
          "streak": {
            "count": 5,
            "type": "hit"
          },
          "confidence": 79.9
        }
      ],
      "score": 81.9,
      "correlated": false
    },
    {
      "legs": [
        {
          "id": 1630558,
          "name": "Davion Mitchell",
          "team": "MIA",
          "position": "G",
          "stat": "pts",
          "label": "Points",
          "odds_type": "standard",
          "line": 7.5,
          "hit_rate": 0.8,
          "hit_rate_l5": 1.0,
          "hit_rate_season": 0.702,
          "avg_l5": 13.0,
          "avg_l10": 9.1,
          "avg_season": 9.0,
          "edge": 5.5,
          "hits": 8,
          "sample": 10,
          "matchup_mult": 0.974,
          "opponent": "CHA",
          "location": "Road",
          "streak": {
            "count": 5,
            "type": "hit"
          },
          "confidence": 84.9
        },
        {
          "id": 1630224,
          "name": "Jalen Green",
          "team": "PHX",
          "position": "G",
          "stat": "pr",
          "label": "Pts+Rebs",
          "odds_type": "standard",
          "line": 27.5,
          "hit_rate": 0.6,
          "hit_rate_l5": 1.0,
          "hit_rate_season": 0.4,
          "avg_l5": 32.6,
          "avg_l10": 26.1,
          "avg_season": 21.1,
          "edge": 5.1,
          "hits": 6,
          "sample": 10,
          "matchup_mult": 0.999,
          "opponent": "MIN",
          "location": "Road",
          "streak": {
            "count": 6,
            "type": "hit"
          },
          "confidence": 81.0
        },
        {
          "id": 201566,
          "name": "Russell Westbrook",
          "team": "SAC",
          "position": "G",
          "stat": "ast",
          "label": "Assists",
          "odds_type": "standard",
          "line": 6.5,
          "hit_rate": 0.6,
          "hit_rate_l5": 1.0,
          "hit_rate_season": 0.484,
          "avg_l5": 9.7,
          "avg_l10": 6.6,
          "avg_season": 6.6,
          "edge": 3.2,
          "hits": 6,
          "sample": 10,
          "matchup_mult": 0.979,
          "opponent": "SAS",
          "location": "Home",
          "streak": {
            "count": 5,
            "type": "hit"
          },
          "confidence": 79.9
        }
      ],
      "score": 81.9,
      "correlated": false
    },
    {
      "legs": [
        {
          "id": 1630558,
          "name": "Davion Mitchell",
          "team": "MIA",
          "position": "G",
          "stat": "pr",
          "label": "Pts+Rebs",
          "odds_type": "standard",
          "line": 9.5,
          "hit_rate": 0.8,
          "hit_rate_l5": 1.0,
          "hit_rate_season": 0.702,
          "avg_l5": 17.0,
          "avg_l10": 12.5,
          "avg_season": 11.7,
          "edge": 7.5,
          "hits": 8,
          "sample": 10,
          "matchup_mult": 0.974,
          "opponent": "CHA",
          "location": "Road",
          "streak": {
            "count": 5,
            "type": "hit"
          },
          "confidence": 84.9
        },
        {
          "id": 201566,
          "name": "Russell Westbrook",
          "team": "SAC",
          "position": "G",
          "stat": "ast",
          "label": "Assists",
          "odds_type": "standard",
          "line": 6.5,
          "hit_rate": 0.6,
          "hit_rate_l5": 1.0,
          "hit_rate_season": 0.484,
          "avg_l5": 9.7,
          "avg_l10": 6.6,
          "avg_season": 6.6,
          "edge": 3.2,
          "hits": 6,
          "sample": 10,
          "matchup_mult": 0.979,
          "opponent": "SAS",
          "location": "Home",
          "streak": {
            "count": 5,
            "type": "hit"
          },
          "confidence": 79.9
        },
        {
          "id": 1626164,
          "name": "Devin Booker",
          "team": "PHX",
          "position": "G",
          "stat": "pr",
          "label": "Pts+Rebs",
          "odds_type": "standard",
          "line": 31.5,
          "hit_rate": 0.7,
          "hit_rate_l5": 1.0,
          "hit_rate_season": 0.423,
          "avg_l5": 38.4,
          "avg_l10": 33.9,
          "avg_season": 29.7,
          "edge": 6.9,
          "hits": 7,
          "sample": 10,
          "matchup_mult": 0.999,
          "opponent": "MIN",
          "location": "Road",
          "streak": {
            "count": 7,
            "type": "hit"
          },
          "confidence": 78.8
        }
      ],
      "score": 81.2,
      "correlated": false
    },
    {
      "legs": [
        {
          "id": 1630558,
          "name": "Davion Mitchell",
          "team": "MIA",
          "position": "G",
          "stat": "pts",
          "label": "Points",
          "odds_type": "standard",
          "line": 7.5,
          "hit_rate": 0.8,
          "hit_rate_l5": 1.0,
          "hit_rate_season": 0.702,
          "avg_l5": 13.0,
          "avg_l10": 9.1,
          "avg_season": 9.0,
          "edge": 5.5,
          "hits": 8,
          "sample": 10,
          "matchup_mult": 0.974,
          "opponent": "CHA",
          "location": "Road",
          "streak": {
            "count": 5,
            "type": "hit"
          },
          "confidence": 84.9
        },
        {
          "id": 201566,
          "name": "Russell Westbrook",
          "team": "SAC",
          "position": "G",
          "stat": "ast",
          "label": "Assists",
          "odds_type": "standard",
          "line": 6.5,
          "hit_rate": 0.6,
          "hit_rate_l5": 1.0,
          "hit_rate_season": 0.484,
          "avg_l5": 9.7,
          "avg_l10": 6.6,
          "avg_season": 6.6,
          "edge": 3.2,
          "hits": 6,
          "sample": 10,
          "matchup_mult": 0.979,
          "opponent": "SAS",
          "location": "Home",
          "streak": {
            "count": 5,
            "type": "hit"
          },
          "confidence": 79.9
        },
        {
          "id": 1626164,
          "name": "Devin Booker",
          "team": "PHX",
          "position": "G",
          "stat": "pr",
          "label": "Pts+Rebs",
          "odds_type": "standard",
          "line": 31.5,
          "hit_rate": 0.7,
          "hit_rate_l5": 1.0,
          "hit_rate_season": 0.423,
          "avg_l5": 38.4,
          "avg_l10": 33.9,
          "avg_season": 29.7,
          "edge": 6.9,
          "hits": 7,
          "sample": 10,
          "matchup_mult": 0.999,
          "opponent": "MIN",
          "location": "Road",
          "streak": {
            "count": 7,
            "type": "hit"
          },
          "confidence": 78.8
        }
      ],
      "score": 81.2,
      "correlated": false
    },
    {
      "legs": [
        {
          "id": 1630558,
          "name": "Davion Mitchell",
          "team": "MIA",
          "position": "G",
          "stat": "pr",
          "label": "Pts+Rebs",
          "odds_type": "standard",
          "line": 9.5,
          "hit_rate": 0.8,
          "hit_rate_l5": 1.0,
          "hit_rate_season": 0.702,
          "avg_l5": 17.0,
          "avg_l10": 12.5,
          "avg_season": 11.7,
          "edge": 7.5,
          "hits": 8,
          "sample": 10,
          "matchup_mult": 0.974,
          "opponent": "CHA",
          "location": "Road",
          "streak": {
            "count": 5,
            "type": "hit"
          },
          "confidence": 84.9
        },
        {
          "id": 1630224,
          "name": "Jalen Green",
          "team": "PHX",
          "position": "G",
          "stat": "pr",
          "label": "Pts+Rebs",
          "odds_type": "standard",
          "line": 27.5,
          "hit_rate": 0.6,
          "hit_rate_l5": 1.0,
          "hit_rate_season": 0.4,
          "avg_l5": 32.6,
          "avg_l10": 26.1,
          "avg_season": 21.1,
          "edge": 5.1,
          "hits": 6,
          "sample": 10,
          "matchup_mult": 0.999,
          "opponent": "MIN",
          "location": "Road",
          "streak": {
            "count": 6,
            "type": "hit"
          },
          "confidence": 81.0
        },
        {
          "id": 1641724,
          "name": "Jett Howard",
          "team": "ORL",
          "position": "G",
          "stat": "pr",
          "label": "Pts+Rebs",
          "odds_type": "standard",
          "line": 8.5,
          "hit_rate": 0.7,
          "hit_rate_l5": 1.0,
          "hit_rate_season": 0.356,
          "avg_l5": 13.4,
          "avg_l10": 11.6,
          "avg_season": 6.4,
          "edge": 4.9,
          "hits": 7,
          "sample": 10,
          "matchup_mult": 0.934,
          "opponent": "OKC",
          "location": "Home",
          "streak": {
            "count": 6,
            "type": "hit"
          },
          "confidence": 76.1
        }
      ],
      "score": 80.7,
      "correlated": false
    },
    {
      "legs": [
        {
          "id": 1630558,
          "name": "Davion Mitchell",
          "team": "MIA",
          "position": "G",
          "stat": "pts",
          "label": "Points",
          "odds_type": "standard",
          "line": 7.5,
          "hit_rate": 0.8,
          "hit_rate_l5": 1.0,
          "hit_rate_season": 0.702,
          "avg_l5": 13.0,
          "avg_l10": 9.1,
          "avg_season": 9.0,
          "edge": 5.5,
          "hits": 8,
          "sample": 10,
          "matchup_mult": 0.974,
          "opponent": "CHA",
          "location": "Road",
          "streak": {
            "count": 5,
            "type": "hit"
          },
          "confidence": 84.9
        },
        {
          "id": 1630224,
          "name": "Jalen Green",
          "team": "PHX",
          "position": "G",
          "stat": "pr",
          "label": "Pts+Rebs",
          "odds_type": "standard",
          "line": 27.5,
          "hit_rate": 0.6,
          "hit_rate_l5": 1.0,
          "hit_rate_season": 0.4,
          "avg_l5": 32.6,
          "avg_l10": 26.1,
          "avg_season": 21.1,
          "edge": 5.1,
          "hits": 6,
          "sample": 10,
          "matchup_mult": 0.999,
          "opponent": "MIN",
          "location": "Road",
          "streak": {
            "count": 6,
            "type": "hit"
          },
          "confidence": 81.0
        },
        {
          "id": 1641724,
          "name": "Jett Howard",
          "team": "ORL",
          "position": "G",
          "stat": "pr",
          "label": "Pts+Rebs",
          "odds_type": "standard",
          "line": 8.5,
          "hit_rate": 0.7,
          "hit_rate_l5": 1.0,
          "hit_rate_season": 0.356,
          "avg_l5": 13.4,
          "avg_l10": 11.6,
          "avg_season": 6.4,
          "edge": 4.9,
          "hits": 7,
          "sample": 10,
          "matchup_mult": 0.934,
          "opponent": "OKC",
          "location": "Home",
          "streak": {
            "count": 6,
            "type": "hit"
          },
          "confidence": 76.1
        }
      ],
      "score": 80.7,
      "correlated": false
    },
    {
      "legs": [
        {
          "id": 1630558,
          "name": "Davion Mitchell",
          "team": "MIA",
          "position": "G",
          "stat": "pr",
          "label": "Pts+Rebs",
          "odds_type": "standard",
          "line": 9.5,
          "hit_rate": 0.8,
          "hit_rate_l5": 1.0,
          "hit_rate_season": 0.702,
          "avg_l5": 17.0,
          "avg_l10": 12.5,
          "avg_season": 11.7,
          "edge": 7.5,
          "hits": 8,
          "sample": 10,
          "matchup_mult": 0.974,
          "opponent": "CHA",
          "location": "Road",
          "streak": {
            "count": 5,
            "type": "hit"
          },
          "confidence": 84.9
        },
        {
          "id": 1630224,
          "name": "Jalen Green",
          "team": "PHX",
          "position": "G",
          "stat": "pr",
          "label": "Pts+Rebs",
          "odds_type": "standard",
          "line": 27.5,
          "hit_rate": 0.6,
          "hit_rate_l5": 1.0,
          "hit_rate_season": 0.4,
          "avg_l5": 32.6,
          "avg_l10": 26.1,
          "avg_season": 21.1,
          "edge": 5.1,
          "hits": 6,
          "sample": 10,
          "matchup_mult": 0.999,
          "opponent": "MIN",
          "location": "Road",
          "streak": {
            "count": 6,
            "type": "hit"
          },
          "confidence": 81.0
        },
        {
          "id": 1641724,
          "name": "Jett Howard",
          "team": "ORL",
          "position": "G",
          "stat": "pra",
          "label": "Pts+Rebs+Asts",
          "odds_type": "standard",
          "line": 9.0,
          "hit_rate": 0.7,
          "hit_rate_l5": 1.0,
          "hit_rate_season": 0.311,
          "avg_l5": 14.4,
          "avg_l10": 12.8,
          "avg_season": 7.2,
          "edge": 5.4,
          "hits": 7,
          "sample": 10,
          "matchup_mult": 0.934,
          "opponent": "OKC",
          "location": "Home",
          "streak": {
            "count": 6,
            "type": "hit"
          },
          "confidence": 75.5
        }
      ],
      "score": 80.5,
      "correlated": false
    },
    {
      "legs": [
        {
          "id": 1630558,
          "name": "Davion Mitchell",
          "team": "MIA",
          "position": "G",
          "stat": "pts",
          "label": "Points",
          "odds_type": "standard",
          "line": 7.5,
          "hit_rate": 0.8,
          "hit_rate_l5": 1.0,
          "hit_rate_season": 0.702,
          "avg_l5": 13.0,
          "avg_l10": 9.1,
          "avg_season": 9.0,
          "edge": 5.5,
          "hits": 8,
          "sample": 10,
          "matchup_mult": 0.974,
          "opponent": "CHA",
          "location": "Road",
          "streak": {
            "count": 5,
            "type": "hit"
          },
          "confidence": 84.9
        },
        {
          "id": 1630224,
          "name": "Jalen Green",
          "team": "PHX",
          "position": "G",
          "stat": "pr",
          "label": "Pts+Rebs",
          "odds_type": "standard",
          "line": 27.5,
          "hit_rate": 0.6,
          "hit_rate_l5": 1.0,
          "hit_rate_season": 0.4,
          "avg_l5": 32.6,
          "avg_l10": 26.1,
          "avg_season": 21.1,
          "edge": 5.1,
          "hits": 6,
          "sample": 10,
          "matchup_mult": 0.999,
          "opponent": "MIN",
          "location": "Road",
          "streak": {
            "count": 6,
            "type": "hit"
          },
          "confidence": 81.0
        },
        {
          "id": 1641724,
          "name": "Jett Howard",
          "team": "ORL",
          "position": "G",
          "stat": "pra",
          "label": "Pts+Rebs+Asts",
          "odds_type": "standard",
          "line": 9.0,
          "hit_rate": 0.7,
          "hit_rate_l5": 1.0,
          "hit_rate_season": 0.311,
          "avg_l5": 14.4,
          "avg_l10": 12.8,
          "avg_season": 7.2,
          "edge": 5.4,
          "hits": 7,
          "sample": 10,
          "matchup_mult": 0.934,
          "opponent": "OKC",
          "location": "Home",
          "streak": {
            "count": 6,
            "type": "hit"
          },
          "confidence": 75.5
        }
      ],
      "score": 80.5,
      "correlated": false
    },
    {
      "legs": [
        {
          "id": 1630558,
          "name": "Davion Mitchell",
          "team": "MIA",
          "position": "G",
          "stat": "pr",
          "label": "Pts+Rebs",
          "odds_type": "standard",
          "line": 9.5,
          "hit_rate": 0.8,
          "hit_rate_l5": 1.0,
          "hit_rate_season": 0.702,
          "avg_l5": 17.0,
          "avg_l10": 12.5,
          "avg_season": 11.7,
          "edge": 7.5,
          "hits": 8,
          "sample": 10,
          "matchup_mult": 0.974,
          "opponent": "CHA",
          "location": "Road",
          "streak": {
            "count": 5,
            "type": "hit"
          },
          "confidence": 84.9
        },
        {
          "id": 201566,
          "name": "Russell Westbrook",
          "team": "SAC",
          "position": "G",
          "stat": "ast",
          "label": "Assists",
          "odds_type": "standard",
          "line": 6.5,
          "hit_rate": 0.6,
          "hit_rate_l5": 1.0,
          "hit_rate_season": 0.484,
          "avg_l5": 9.7,
          "avg_l10": 6.6,
          "avg_season": 6.6,
          "edge": 3.2,
          "hits": 6,
          "sample": 10,
          "matchup_mult": 0.979,
          "opponent": "SAS",
          "location": "Home",
          "streak": {
            "count": 5,
            "type": "hit"
          },
          "confidence": 79.9
        },
        {
          "id": 1641724,
          "name": "Jett Howard",
          "team": "ORL",
          "position": "G",
          "stat": "pr",
          "label": "Pts+Rebs",
          "odds_type": "standard",
          "line": 8.5,
          "hit_rate": 0.7,
          "hit_rate_l5": 1.0,
          "hit_rate_season": 0.356,
          "avg_l5": 13.4,
          "avg_l10": 11.6,
          "avg_season": 6.4,
          "edge": 4.9,
          "hits": 7,
          "sample": 10,
          "matchup_mult": 0.934,
          "opponent": "OKC",
          "location": "Home",
          "streak": {
            "count": 6,
            "type": "hit"
          },
          "confidence": 76.1
        }
      ],
      "score": 80.3,
      "correlated": false
    },
    {
      "legs": [
        {
          "id": 1630558,
          "name": "Davion Mitchell",
          "team": "MIA",
          "position": "G",
          "stat": "pts",
          "label": "Points",
          "odds_type": "standard",
          "line": 7.5,
          "hit_rate": 0.8,
          "hit_rate_l5": 1.0,
          "hit_rate_season": 0.702,
          "avg_l5": 13.0,
          "avg_l10": 9.1,
          "avg_season": 9.0,
          "edge": 5.5,
          "hits": 8,
          "sample": 10,
          "matchup_mult": 0.974,
          "opponent": "CHA",
          "location": "Road",
          "streak": {
            "count": 5,
            "type": "hit"
          },
          "confidence": 84.9
        },
        {
          "id": 201566,
          "name": "Russell Westbrook",
          "team": "SAC",
          "position": "G",
          "stat": "ast",
          "label": "Assists",
          "odds_type": "standard",
          "line": 6.5,
          "hit_rate": 0.6,
          "hit_rate_l5": 1.0,
          "hit_rate_season": 0.484,
          "avg_l5": 9.7,
          "avg_l10": 6.6,
          "avg_season": 6.6,
          "edge": 3.2,
          "hits": 6,
          "sample": 10,
          "matchup_mult": 0.979,
          "opponent": "SAS",
          "location": "Home",
          "streak": {
            "count": 5,
            "type": "hit"
          },
          "confidence": 79.9
        },
        {
          "id": 1641724,
          "name": "Jett Howard",
          "team": "ORL",
          "position": "G",
          "stat": "pr",
          "label": "Pts+Rebs",
          "odds_type": "standard",
          "line": 8.5,
          "hit_rate": 0.7,
          "hit_rate_l5": 1.0,
          "hit_rate_season": 0.356,
          "avg_l5": 13.4,
          "avg_l10": 11.6,
          "avg_season": 6.4,
          "edge": 4.9,
          "hits": 7,
          "sample": 10,
          "matchup_mult": 0.934,
          "opponent": "OKC",
          "location": "Home",
          "streak": {
            "count": 6,
            "type": "hit"
          },
          "confidence": 76.1
        }
      ],
      "score": 80.3,
      "correlated": false
    }
  ]
}