{
  "hot_streaks": [
    {
      "id": 1628368,
      "name": "De'Aaron Fox",
      "team": "SAS",
      "position": "G",
      "stat": "ast",
      "label": "Assists",
      "line": 5.5,
      "avg": 6.2,
      "hit_rate": 0.8,
      "sample": 10,
      "hits": 8,
      "streak": 4
    },
    {
      "id": 1628379,
      "name": "Luke Kennard",
      "team": "LAL",
      "position": "G",
      "stat": "sa",
      "label": "STL+AST",
      "line": 1.5,
      "avg": 1.8,
      "hit_rate": 0.8,
      "sample": 10,
      "hits": 8,
      "streak": 4
    },
    {
      "id": 1628969,
      "name": "Mikal Bridges",
      "team": "NYK",
      "position": "SG",
      "stat": "pts",
      "label": "Points",
      "line": 13.0,
      "avg": 11.2,
      "hit_rate": 0.4,
      "sample": 10,
      "hits": 4,
      "streak": 4
    },
    {
      "id": 1629651,
      "name": "Nic Claxton",
      "team": "BKN",
      "position": "C",
      "stat": "sa",
      "label": "STL+AST",
      "line": 2.5,
      "avg": 2.5,
      "hit_rate": 0.6,
      "sample": 10,
      "hits": 6,
      "streak": 4
    },
    {
      "id": 1630230,
      "name": "Naji Marshall",
      "team": "DAL",
      "position": "F",
      "stat": "pr",
      "label": "PTS+REB",
      "line": 21.5,
      "avg": 22.8,
      "hit_rate": 0.7,
      "sample": 10,
      "hits": 7,
      "streak": 4
    },
    {
      "id": 1630552,
      "name": "Jalen Johnson",
      "team": "ATL",
      "position": "F",
      "stat": "pr",
      "label": "PTS+REB",
      "line": 30.5,
      "avg": 31.6,
      "hit_rate": 0.7,
      "sample": 10,
      "hits": 7,
      "streak": 4
    },
    {
      "id": 1641705,
      "name": "Victor Wembanyama",
      "team": "SAS",
      "position": "PF",
      "stat": "reb",
      "label": "Rebounds",
      "line": 14.0,
      "avg": 12.0,
      "hit_rate": 0.4,
      "sample": 10,
      "hits": 4,
      "streak": 4
    },
    {
      "id": 1641764,
      "name": "Brandin Podziemski",
      "team": "GSW",
      "position": "G",
      "stat": "pts",
      "label": "Points",
      "line": 18.5,
      "avg": 16.9,
      "hit_rate": 0.6,
      "sample": 10,
      "hits": 6,
      "streak": 4
    },
    {
      "id": 1641764,
      "name": "Brandin Podziemski",
      "team": "GSW",
      "position": "G",
      "stat": "pr",
      "label": "PTS+REB",
      "line": 24.5,
      "avg": 23.9,
      "hit_rate": 0.6,
      "sample": 10,
      "hits": 6,
      "streak": 4
    },
    {
      "id": 1641764,
      "name": "Brandin Podziemski",
      "team": "GSW",
      "position": "G",
      "stat": "pa",
      "label": "PTS+AST",
      "line": 22.5,
      "avg": 21.7,
      "hit_rate": 0.6,
      "sample": 10,
      "hits": 6,
      "streak": 4
    },
    {
      "id": 1641764,
      "name": "Brandin Podziemski",
      "team": "GSW",
      "position": "G",
      "stat": "pra",
      "label": "PTS+REB+AST",
      "line": 29.0,
      "avg": 27.9,
      "hit_rate": 0.6,
      "sample": 10,
      "hits": 6,
      "streak": 4
    },
    {
      "id": 201942,
      "name": "DeMar DeRozan",
      "team": "SAC",
      "position": "SG",
      "stat": "reb",
      "label": "Rebounds",
      "line": 3.5,
      "avg": 2.5,
      "hit_rate": 0.5,
      "sample": 10,
      "hits": 5,
      "streak": 3
    },
    {
      "id": 201950,
      "name": "Jrue Holiday",
      "team": "POR",
      "position": "G",
      "stat": "fg3m",
      "label": "3PM",
      "line": 2.5,
      "avg": 2.6,
      "hit_rate": 0.5,
      "sample": 10,
      "hits": 5,
      "streak": 3
    },
    {
      "id": 203076,
      "name": "Anthony Davis",
      "team": "WAS",
      "position": "PF",
      "stat": "pts",
      "label": "Points",
      "line": 16.5,
      "avg": 20.4,
      "hit_rate": 0.7,
      "sample": 10,
      "hits": 7,
      "streak": 3
    },
    {
      "id": 203076,
      "name": "Anthony Davis",
      "team": "WAS",
      "position": "PF",
      "stat": "reb",
      "label": "Rebounds",
      "line": 10.0,
      "avg": 11.0,
      "hit_rate": 0.7,
      "sample": 10,
      "hits": 7,
      "streak": 3
    },
    {
      "id": 203076,
      "name": "Anthony Davis",
      "team": "WAS",
      "position": "PF",
      "stat": "pr",
      "label": "PTS+REB",
      "line": 26.5,
      "avg": 33.0,
      "hit_rate": 0.8,
      "sample": 10,
      "hits": 8,
      "streak": 3
    },
    {
      "id": 203076,
      "name": "Anthony Davis",
      "team": "WAS",
      "position": "PF",
      "stat": "pa",
      "label": "PTS+AST",
      "line": 18.5,
      "avg": 23.5,
      "hit_rate": 0.7,
      "sample": 10,
      "hits": 7,
      "streak": 3
    },
    {
      "id": 203076,
      "name": "Anthony Davis",
      "team": "WAS",
      "position": "PF",
      "stat": "ra",
      "label": "REB+AST",
      "line": 12.0,
      "avg": 14.3,
      "hit_rate": 0.8,
      "sample": 10,
      "hits": 8,
      "streak": 3
    },
    {
      "id": 203076,
      "name": "Anthony Davis",
      "team": "WAS",
      "position": "PF",
      "stat": "pra",
      "label": "PTS+REB+AST",
      "line": 28.5,
      "avg": 35.4,
      "hit_rate": 0.8,
      "sample": 10,
      "hits": 8,
      "streak": 3
    },
    {
      "id": 203648,
      "name": "Thanasis Antetokounmpo",
      "team": "MIL",
      "position": "F",
      "stat": "ra",
      "label": "REB+AST",
      "line": 3.0,
      "avg": 1.9,
      "hit_rate": 0.4,
      "sample": 10,
      "hits": 4,
      "streak": 3
    },
    {
      "id": 203924,
      "name": "Jerami Grant",
      "team": "POR",
      "position": "F",
      "stat": "pts",
      "label": "Points",
      "line": 16.5,
      "avg": 17.6,
      "hit_rate": 0.7,
      "sample": 10,
      "hits": 7,
      "streak": 3
    },
    {
      "id": 203937,
      "name": "Kyle Anderson",
      "team": "MIN",
      "position": "SF",
      "stat": "bs",
      "label": "BLK+STL",
      "line": 1.5,
      "avg": 1.3,
      "hit_rate": 0.3,
      "sample": 10,
      "hits": 3,
      "streak": 3
    },
    {
      "id": 203939,
      "name": "Dwight Powell",
      "team": "DAL",
      "position": "PF",
      "stat": "stl",
      "label": "Steals",
      "line": 0.5,
      "avg": 0.4,
      "hit_rate": 0.4,
      "sample": 10,
      "hits": 4,
      "streak": 3
    },
    {
      "id": 203939,
      "name": "Dwight Powell",
      "team": "DAL",
      "position": "PF",
      "stat": "pr",
      "label": "PTS+REB",
      "line": 8.5,
      "avg": 7.5,
      "hit_rate": 0.4,
      "sample": 10,
      "hits": 4,
      "streak": 3
    },
    {
      "id": 203939,
      "name": "Dwight Powell",
      "team": "DAL",
      "position": "PF",
      "stat": "pa",
      "label": "PTS+AST",
      "line": 6.0,
      "avg": 4.6,
      "hit_rate": 0.4,
      "sample": 10,
      "hits": 4,
      "streak": 3
    },
    {
      "id": 203939,
      "name": "Dwight Powell",
      "team": "DAL",
      "position": "PF",
      "stat": "pra",
      "label": "PTS+REB+AST",
      "line": 10.0,
      "avg": 8.5,
      "hit_rate": 0.4,
      "sample": 10,
      "hits": 4,
      "streak": 3
    },
    {
      "id": 203991,
      "name": "Clint Capela",
      "team": "HOU",
      "position": "C",
      "stat": "blk",
      "label": "Blocks",
      "line": 1.0,
      "avg": 1.0,
      "hit_rate": 0.4,
      "sample": 10,
      "hits": 4,
      "streak": 3
    },
    {
      "id": 203991,
      "name": "Clint Capela",
      "team": "HOU",
      "position": "C",
      "stat": "bs",
      "label": "BLK+STL",
      "line": 1.5,
      "avg": 1.5,
      "hit_rate": 0.5,
      "sample": 10,
      "hits": 5,
      "streak": 3
    },
    {
      "id": 1626156,
      "name": "D'Angelo Russell",
      "team": "WAS",
      "position": "G",
      "stat": "pts",
      "label": "Points",
      "line": 5.5,
      "avg": 9.0,
      "hit_rate": 0.6,
      "sample": 10,
      "hits": 6,
      "streak": 3
    },
    {
      "id": 1626156,
      "name": "D'Angelo Russell",
      "team": "WAS",
      "position": "G",
      "stat": "ast",
      "label": "Assists",
      "line": 2.5,
      "avg": 3.7,
      "hit_rate": 0.4,
      "sample": 10,
      "hits": 4,
      "streak": 3
    }
  ],
  "top_hitters": [
    {
      "id": 1630314,
      "name": "Brandon Williams",
      "team": "DAL",
      "position": "G",
      "stat": "pts",
      "label": "Points",
      "line": 9.5,
      "avg": 13.2,
      "hit_rate": 0.9,
      "sample": 10,
      "hits": 9
    },
    {
      "id": 1630314,
      "name": "Brandon Williams",
      "team": "DAL",
      "position": "G",
      "stat": "pa",
      "label": "PTS+AST",
      "line": 14.5,
      "avg": 15.4,
      "hit_rate": 0.9,
      "sample": 10,
      "hits": 9
    },
    {
      "id": 1641710,
      "name": "Anthony Black",
      "team": "ORL",
      "position": "G",
      "stat": "pts",
      "label": "Points",
      "line": 7.0,
      "avg": 14.4,
      "hit_rate": 0.9,
      "sample": 10,
      "hits": 9
    },
    {
      "id": 1641710,
      "name": "Anthony Black",
      "team": "ORL",
      "position": "G",
      "stat": "pa",
      "label": "PTS+AST",
      "line": 9.0,
      "avg": 15.1,
      "hit_rate": 0.9,
      "sample": 10,
      "hits": 9
    },
    {
      "id": 1641726,
      "name": "Dereck Lively II",
      "team": "DAL",
      "position": "C",
      "stat": "pts",
      "label": "Points",
      "line": 3.5,
      "avg": 4.3,
      "hit_rate": 0.857,
      "sample": 7,
      "hits": 6
    },
    {
      "id": 203076,
      "name": "Anthony Davis",
      "team": "WAS",
      "position": "PF",
      "stat": "pr",
      "label": "PTS+REB",
      "line": 26.5,
      "avg": 33.0,
      "hit_rate": 0.8,
      "sample": 10,
      "hits": 8
    },
    {
      "id": 203076,
      "name": "Anthony Davis",
      "team": "WAS",
      "position": "PF",
      "stat": "ra",
      "label": "REB+AST",
      "line": 12.0,
      "avg": 14.3,
      "hit_rate": 0.8,
      "sample": 10,
      "hits": 8
    },
    {
      "id": 203076,
      "name": "Anthony Davis",
      "team": "WAS",
      "position": "PF",
      "stat": "pra",
      "label": "PTS+REB+AST",
      "line": 28.5,
      "avg": 35.4,
      "hit_rate": 0.8,
      "sample": 10,
      "hits": 8
    },
    {
      "id": 203903,
      "name": "Jordan Clarkson",
      "team": "NYK",
      "position": "G",
      "stat": "pts",
      "label": "Points",
      "line": 7.5,
      "avg": 7.9,
      "hit_rate": 0.8,
      "sample": 10,
      "hits": 8
    },
    {
      "id": 203994,
      "name": "Jusuf Nurki\u0107",
      "team": "UTA",
      "position": "C",
      "stat": "pts",
      "label": "Points",
      "line": 8.5,
      "avg": 13.7,
      "hit_rate": 0.8,
      "sample": 10,
      "hits": 8
    },
    {
      "id": 203994,
      "name": "Jusuf Nurki\u0107",
      "team": "UTA",
      "position": "C",
      "stat": "sa",
      "label": "STL+AST",
      "line": 4.0,
      "avg": 7.1,
      "hit_rate": 0.8,
      "sample": 10,
      "hits": 8
    },
    {
      "id": 1626204,
      "name": "Larry Nance Jr.",
      "team": "CLE",
      "position": "PF",
      "stat": "sa",
      "label": "STL+AST",
      "line": 0.5,
      "avg": 1.1,
      "hit_rate": 0.8,
      "sample": 10,
      "hits": 8
    },
    {
      "id": 1627741,
      "name": "Buddy Hield",
      "team": "ATL",
      "position": "G",
      "stat": "pra",
      "label": "PTS+REB+AST",
      "line": 2.5,
      "avg": 7.9,
      "hit_rate": 0.8,
      "sample": 10,
      "hits": 8
    },
    {
      "id": 1627747,
      "name": "Caris LeVert",
      "team": "DET",
      "position": "G",
      "stat": "stl",
      "label": "Steals",
      "line": 0.5,
      "avg": 0.8,
      "hit_rate": 0.8,
      "sample": 10,
      "hits": 8
    },
    {
      "id": 1627749,
      "name": "Dejounte Murray",
      "team": "NOP",
      "position": "G",
      "stat": "pr",
      "label": "PTS+REB",
      "line": 18.0,
      "avg": 23.5,
      "hit_rate": 0.8,
      "sample": 10,
      "hits": 8
    },
    {
      "id": 1627827,
      "name": "Dorian Finney-Smith",
      "team": "HOU",
      "position": "F",
      "stat": "reb",
      "label": "Rebounds",
      "line": 1.5,
      "avg": 2.5,
      "hit_rate": 0.8,
      "sample": 10,
      "hits": 8
    },
    {
      "id": 1627936,
      "name": "Alex Caruso",
      "team": "OKC",
      "position": "G",
      "stat": "stl",
      "label": "Steals",
      "line": 0.5,
      "avg": 1.2,
      "hit_rate": 0.8,
      "sample": 10,
      "hits": 8
    },
    {
      "id": 1627936,
      "name": "Alex Caruso",
      "team": "OKC",
      "position": "G",
      "stat": "bs",
      "label": "BLK+STL",
      "line": 0.5,
      "avg": 1.5,
      "hit_rate": 0.8,
      "sample": 10,
      "hits": 8
    },
    {
      "id": 1628368,
      "name": "De'Aaron Fox",
      "team": "SAS",
      "position": "G",
      "stat": "ast",
      "label": "Assists",
      "line": 5.5,
      "avg": 6.2,
      "hit_rate": 0.8,
      "sample": 10,
      "hits": 8
    },
    {
      "id": 1628368,
      "name": "De'Aaron Fox",
      "team": "SAS",
      "position": "G",
      "stat": "pa",
      "label": "PTS+AST",
      "line": 19.5,
      "avg": 23.4,
      "hit_rate": 0.8,
      "sample": 10,
      "hits": 8
    },
    {
      "id": 1628378,
      "name": "Donovan Mitchell",
      "team": "CLE",
      "position": "G",
      "stat": "ra",
      "label": "REB+AST",
      "line": 8.5,
      "avg": 9.4,
      "hit_rate": 0.8,
      "sample": 10,
      "hits": 8
    },
    {
      "id": 1628379,
      "name": "Luke Kennard",
      "team": "LAL",
      "position": "G",
      "stat": "sa",
      "label": "STL+AST",
      "line": 1.5,
      "avg": 1.8,
      "hit_rate": 0.8,
      "sample": 10,
      "hits": 8
    },
    {
      "id": 1628384,
      "name": "OG Anunoby",
      "team": "NYK",
      "position": "SF",
      "stat": "pr",
      "label": "PTS+REB",
      "line": 17.0,
      "avg": 22.2,
      "hit_rate": 0.8,
      "sample": 10,
      "hits": 8
    },
    {
      "id": 1628386,
      "name": "Jarrett Allen",
      "team": "CLE",
      "position": "C",
      "stat": "reb",
      "label": "Rebounds",
      "line": 8.0,
      "avg": 9.5,
      "hit_rate": 0.8,
      "sample": 10,
      "hits": 8
    },
    {
      "id": 1628386,
      "name": "Jarrett Allen",
      "team": "CLE",
      "position": "C",
      "stat": "ra",
      "label": "REB+AST",
      "line": 9.0,
      "avg": 10.8,
      "hit_rate": 0.8,
      "sample": 10,
      "hits": 8
    },
    {
      "id": 1628415,
      "name": "Dillon Brooks",
      "team": "PHX",
      "position": "SG",
      "stat": "pts",
      "label": "Points",
      "line": 20.5,
      "avg": 20.4,
      "hit_rate": 0.8,
      "sample": 10,
      "hits": 8
    },
    {
      "id": 1628415,
      "name": "Dillon Brooks",
      "team": "PHX",
      "position": "SG",
      "stat": "pr",
      "label": "PTS+REB",
      "line": 24.5,
      "avg": 27.1,
      "hit_rate": 0.8,
      "sample": 10,
      "hits": 8
    },
    {
      "id": 1628415,
      "name": "Dillon Brooks",
      "team": "PHX",
      "position": "SG",
      "stat": "pa",
      "label": "PTS+AST",
      "line": 22.0,
      "avg": 24.9,
      "hit_rate": 0.8,
      "sample": 10,
      "hits": 8
    },
    {
      "id": 1628415,
      "name": "Dillon Brooks",
      "team": "PHX",
      "position": "SG",
      "stat": "pra",
      "label": "PTS+REB+AST",
      "line": 26.0,
      "avg": 29.1,
      "hit_rate": 0.8,
      "sample": 10,
      "hits": 8
    },
    {
      "id": 1628973,
      "name": "Jalen Brunson",
      "team": "NYK",
      "position": "G",
      "stat": "pra",
      "label": "PTS+REB+AST",
      "line": 36.0,
      "avg": 38.0,
      "hit_rate": 0.8,
      "sample": 10,
      "hits": 8
    }
  ]
}